appdirs.py
appdirs-1.4.2.dist-info/DESCRIPTION.rst
appdirs-1.4.2.dist-info/METADATA
appdirs-1.4.2.dist-info/RECORD
appdirs-1.4.2.dist-info/WHEEL
appdirs-1.4.2.dist-info/metadata.json
appdirs-1.4.2.dist-info/top_level.txt
