Metadata-Version: 1.1
Name: appdirs
Version: 1.4.2
Summary: A small Python module for determining appropriate platform-specific dirs, e.g. a "user data dir".
Home-page: http://github.com/ActiveState/appdirs
Author: Trent Mick; Sridhar Ratnakumar; Jeff Rouse
Author-email: trentm@gmail.com; github@srid.name; jr@its.to
License: MIT
Keywords: application directory log cache user
Platform: UNKNOWN
Classifier: Development Status :: 4 - Beta
Classifier: Intended Audience :: Developers
Classifier: License :: OSI Approved :: MIT License
Classifier: Operating System :: OS Independent
Classifier: Programming Language :: Python :: 2
Classifier: Programming Language :: Python :: 2.6
Classifier: Programming Language :: Python :: 2.7
Classifier: Programming Language :: Python :: 3
Classifier: Programming Language :: Python :: 3.2
Classifier: Programming Language :: Python :: 3.3
Classifier: Programming Language :: Python :: 3.4
Classifier: Programming Language :: Python :: 3.5
Classifier: Programming Language :: Python :: 3.6
Classifier: Programming Language :: Python :: Implementation :: PyPy
Classifier: Programming Language :: Python :: Implementation :: CPython
Classifier: Topic :: Software Development :: Libraries :: Python Modules
